data_visualiser_package/__init__.py
data_visualiser_package/data_visualiser.py
data_visualiser_package/export_latex_tables.py
data_visualiser_package/py.typed
data_visualiser_package-0.1.0.dist-info/METADATA
data_visualiser_package-0.1.0.dist-info/WHEEL
data_visualiser_package-0.1.0.dist-info/licenses/LICENSE
data_visualiser_package-0.1.0.dist-info/RECORD
