Metadata-Version: 2.4
Name: data-visualiser-package
Version: 0.1.0
Summary: A utility package for data visualization and statistical analysis with Matplotlib and Seaborn
Project-URL: Homepage, https://github.com/jonathan-doenz/data-visualiser-package
Project-URL: Bug Tracker, https://github.com/jonathan-doenz/data-visualiser-package/issues
Author-email: jonathan-doenz <jonathan.doenz@gmail.com>
License: MIT
License-File: LICENSE
Classifier: Development Status :: 4 - Beta
Classifier: Intended Audience :: Science/Research
Classifier: License :: OSI Approved :: MIT License
Classifier: Programming Language :: Python :: 3
Classifier: Programming Language :: Python :: 3.7
Classifier: Programming Language :: Python :: 3.8
Classifier: Programming Language :: Python :: 3.9
Classifier: Programming Language :: Python :: 3.10
Classifier: Programming Language :: Python :: 3.11
Classifier: Topic :: Scientific/Engineering :: Information Analysis
Classifier: Topic :: Scientific/Engineering :: Visualization
Requires-Python: >=3.7
Requires-Dist: matplotlib>=3.3.0
Requires-Dist: numpy>=1.19.0
Requires-Dist: pandas>=1.0.0
Requires-Dist: seaborn>=0.11.0
